ppqueue/__init__.py
ppqueue/__version__.py
ppqueue/exceptions.py
ppqueue/job.py
ppqueue/plot.py
ppqueue/py.typed
ppqueue/queue.py
ppqueue/utils.py
ppqueue/__pycache__/__init__.cpython-310.pyc
ppqueue/__pycache__/__version__.cpython-310.pyc
ppqueue/__pycache__/exceptions.cpython-310.pyc
ppqueue/__pycache__/job.cpython-310.pyc
ppqueue/__pycache__/plot.cpython-310.pyc
ppqueue/__pycache__/queue.cpython-310.pyc
ppqueue/__pycache__/utils.cpython-310.pyc
ppqueue-0.4.0.dist-info/LICENSE
ppqueue-0.4.0.dist-info/METADATA
ppqueue-0.4.0.dist-info/WHEEL
ppqueue-0.4.0.dist-info/entry_points.txt
ppqueue-0.4.0.dist-info/top_level.txt
ppqueue-0.4.0.dist-info/RECORD
